camel_converter/__init__.py
camel_converter/_version.py
camel_converter/decorators.py
camel_converter/py.typed
camel_converter/pydantic_base.py
camel_converter-4.0.0.dist-info/METADATA
camel_converter-4.0.0.dist-info/WHEEL
camel_converter-4.0.0.dist-info/licenses/LICENSE
camel_converter-4.0.0.dist-info/RECORD
