Metadata-Version: 2.3
Name: camel-converter
Version: 4.0.0
Summary: Converts a string from snake case to camel case or camel case to snake case
Author-email: Paul Sanders <paul@paulsanders.dev>
License: MIT License
License-File: LICENSE
Keywords: camel-case,converter,pydantic,python,snake-case
Classifier: Development Status :: 5 - Production/Stable
Classifier: Intended Audience :: Developers
Classifier: License :: OSI Approved :: MIT License
Classifier: Operating System :: OS Independent
Classifier: Programming Language :: Python :: 3.9
Classifier: Programming Language :: Python :: 3.10
Classifier: Programming Language :: Python :: 3.11
Classifier: Programming Language :: Python :: 3.12
Classifier: Typing :: Typed
Requires-Python: >=3.9
Provides-Extra: pydantic
Requires-Dist: pydantic>=2.0.0; extra == 'pydantic'
